Metadata-Version: 1.0
Name: SacLogConverter
Version: 0.1
Summary: convert json to leef and viceversa
Home-page: UNKNOWN
Author: Ahmad Abbas
Author-email: UNKNOWN
License: UNKNOWN
Platform: UNKNOWN
